banchi/__init__.py
banchi/data_service.py
banchi/local_op.py
banchi/serialization.py
banchi/utils.py
banchi/objects/__init__.py
banchi/objects/bond_pb2.py
banchi/objects/calendar_pb2.py
banchi/objects/cashflows_pb2.py
banchi/objects/conversion_pb2.py
banchi/objects/convertible_calc_pb2.py
banchi/objects/convertible_call_schedule_pb2.py
banchi/objects/convertible_pb2.py
banchi/objects/credit_data_pb2.py
banchi/objects/currency_pb2.py
banchi/objects/date_pb2.py
banchi/objects/dividend_protection_pb2.py
banchi/objects/enums_pb2.py
banchi/objects/fx_rate_pb2.py
banchi/objects/interest_rate_index_pb2.py
banchi/objects/make_whole_pb2.py
banchi/objects/market_news_pb2.py
banchi/objects/market_pb2.py
banchi/objects/matrix_pb2.py
banchi/objects/model_parameters_pb2.py
banchi/objects/object_info_pb2.py
banchi/objects/offset_pb2.py
banchi/objects/output_pb2.py
banchi/objects/put_schedule_pb2.py
banchi/objects/query_pb2.py
banchi/objects/stock_pb2.py
banchi/objects/ticker_pb2.py
banchi/objects/trigger_pb2.py
banchi/objects/user_preferences_pb2.py
banchi/objects/warrant_call_schedule_pb2.py
banchi/objects/warrant_pb2.py
banchi/objects/yield_curve_pb2.py
banchi-0.1.8.dist-info/METADATA
banchi-0.1.8.dist-info/WHEEL
banchi-0.1.8.dist-info/top_level.txt
banchi-0.1.8.dist-info/RECORD
