Metadata-Version: 2.1
Name: banchi
Version: 0.1.8
Summary: Financial securities valuation library.
Keywords: convertible,bond,SPAC,warrant,securities,quant
Requires-Dist: protobuf (<4.0,>=3.0)
Provides-Extra: dev
Requires-Dist: matplotlib ; extra == 'dev'
Requires-Dist: jupyterlab ; extra == 'dev'
Requires-Dist: numpy ; extra == 'dev'
Requires-Dist: pytest ; extra == 'dev'
Requires-Dist: build ; extra == 'dev'
Requires-Dist: twine ; extra == 'dev'
Provides-Extra: reports
Requires-Dist: matplotlib ; extra == 'reports'
Requires-Dist: jupyterlab ; extra == 'reports'
Requires-Dist: numpy ; extra == 'reports'
